moorpy/Catenary.py
moorpy/MoorProps.py
moorpy/__init__.py
moorpy/body.py
moorpy/helpers.py
moorpy/line.py
moorpy/lineType.py
moorpy/nonlinear.py
moorpy/point.py
moorpy/subsystem.py
moorpy/system.py
moorpy/library/MoorProps_default.yaml
moorpy/library/MoorProps_newCosts.yaml
moorpy/library/PointProps_default.yaml
moorpy/library/readme.md
moorpy-1.2.1.dist-info/licenses/LICENSE.txt
moorpy-1.2.1.dist-info/METADATA
moorpy-1.2.1.dist-info/WHEEL
moorpy-1.2.1.dist-info/top_level.txt
moorpy-1.2.1.dist-info/RECORD
