Metadata-Version: 2.4
Name: MoorPy
Version: 1.2.1
Summary: A design-oriented mooring system library for Python
Author-email: National Renewable Energy Laboratory <matthew.hall@nrel.gov>
Maintainer-email: Matthew Hall <matthew.hall@nrel.gov>, Stein Housner <stein.housner@nrel.gov>
License: BSD-3-Clause
Project-URL: Homepage, https://github.com/NREL/MoorPy
Project-URL: Documentation, https://moorpy.readthedocs.io
Keywords: wind,floating,mooring,design,water
Classifier: Development Status :: 4 - Beta
Classifier: Intended Audience :: Science/Research
Classifier: Topic :: Scientific/Engineering
Classifier: License :: OSI Approved :: BSD License
Classifier: Programming Language :: Python :: 3
Classifier: Programming Language :: Python :: 3.8
Classifier: Programming Language :: Python :: 3.9
Classifier: Programming Language :: Python :: 3.10
Classifier: Programming Language :: Python :: 3.11
Classifier: Programming Language :: Python :: 3.12
Classifier: Programming Language :: Python :: 3.13
Classifier: Programming Language :: Python :: 3.14
Classifier: Programming Language :: Python :: 3 :: Only
Classifier: Programming Language :: Fortran
Classifier: Operating System :: OS Independent
Requires-Python: >=3.8
License-File: LICENSE.txt
Requires-Dist: matplotlib
Requires-Dist: numpy
Requires-Dist: scipy
Requires-Dist: pyyaml
Provides-Extra: dev
Requires-Dist: pre-commit; extra == "dev"
Provides-Extra: docs
Requires-Dist: sphinx; extra == "docs"
Requires-Dist: sphinx-rtd-theme; extra == "docs"
Provides-Extra: test
Requires-Dist: pytest; extra == "test"
Requires-Dist: pytest-cov; extra == "test"
Requires-Dist: pytest-xdist; extra == "test"
Dynamic: license-file
